setup.py
statemachine.py
statemachine.egg-info/PKG-INFO
statemachine.egg-info/SOURCES.txt
statemachine.egg-info/dependency_links.txt
statemachine.egg-info/top_level.txt