Metadata-Version: 1.0
Name: statemachine
Version: 0.1
Summary: Simple Finite-State Machines
Home-page: https://github.com/kyleconroy/statemachine
Author: Kyle Conroy
Author-email: kyle@kyleconroy.com
License: UNKNOWN
Platform: UNKNOWN
